biomini/__init__.py
biomini/biomini.py
biomini/decorators.py
biomini/enroll.py
biomini/exceptions.py
biomini/utils.py
biomini/examples/__init__.py
biomini/examples/demo.py
biomini/examples/pyqt5_demo.py
python_biomini-1.4.dist-info/LICENSE.txt
python_biomini-1.4.dist-info/METADATA
python_biomini-1.4.dist-info/WHEEL
python_biomini-1.4.dist-info/top_level.txt
python_biomini-1.4.dist-info/RECORD
