Metadata-Version: 2.1
Name: python-biomini
Version: 1.4
Summary: A Python interface for Suprema Biomini fingerprint scanners.
Home-page: https://github.com/pohemati/python-biomini
Download-URL: https://github.com/pohemati/python-biomini/archive/refs/tags/v1.4.tar.gz
Author: Poria Hemati
Author-email: poria.hemati@gmail.com
License: MIT
Keywords: python,suprema,biomini,fingerprint,scanner,enrollment,biometric
Classifier: Operating System :: OS Independent
Classifier: License :: OSI Approved :: MIT License
Classifier: Programming Language :: Python :: 3
License-File: LICENSE.txt
Requires-Dist: pythonnet>=3.0.1
Provides-Extra: pil
Requires-Dist: pillow; extra == "pil"
Provides-Extra: pyqt5
Requires-Dist: pyqt5; extra == "pyqt5"
Provides-Extra: pyqt6
Requires-Dist: pyqt6; extra == "pyqt6"
Provides-Extra: pyside6
Requires-Dist: pyside6; extra == "pyside6"
